{
  "expansions": [
    {
      "name": "core-set",
      "displayName": "Core Set",
      "heroes": {
        "common": [
          {
            "name": "archangel",
            "displayName": "Archangel"
          },
          {
            "name": "hiveguardian",
            "displayName": "Hive Guardian"
          }
        ],
        "uncommon": [
          {
            "name": "katerina",
            "displayName": "Katerina"
          },
          {
            "name": "skullcrasher",
            "displayName": "Skullcrasher"
          }
        ],
        "rare": [
          {
            "name": "quark",
            "displayName": "Quark"
          },
          {
            "name": "spectre",
            "displayName": "Spectre"
          }
        ]
      },
      "actions": {
        "common": [
          {
            "name": "punch",
            "displayName": "Punch",
            "damage": 13
          }
        ],
        "uncommon": [
          {
            "name": "fireball",
            "displayName": "Fireball",
            "damage": 13
          }
        ],
        "rare": []
      }
    }
  ]
}

